pyausaxs/__init__.py
pyausaxs/architecture.py
pyausaxs/integration.py
pyausaxs/loader.py
pyausaxs/__pyinstaller/__init__.py
pyausaxs/__pyinstaller/hook-pyausaxs.py
pyausaxs/__pyinstaller/pyinstaller.py
pyausaxs/resources/libausaxs.dylib
pyausaxs/wrapper/AUSAXS.py
pyausaxs/wrapper/BackendObject.py
pyausaxs/wrapper/Datafile.py
pyausaxs/wrapper/ExactDebye.py
pyausaxs/wrapper/FitResult.py
pyausaxs/wrapper/Histogram.py
pyausaxs/wrapper/IterativeFit.py
pyausaxs/wrapper/Models.py
pyausaxs/wrapper/Molecule.py
pyausaxs/wrapper/PDBfile.py
pyausaxs/wrapper/__init__.py
pyausaxs/wrapper/sasview.py
pyausaxs/wrapper/settings.py
pyausaxs-1.0.10.dist-info/METADATA
pyausaxs-1.0.10.dist-info/WHEEL
pyausaxs-1.0.10.dist-info/entry_points.txt
pyausaxs-1.0.10.dist-info/top_level.txt
pyausaxs-1.0.10.dist-info/RECORD
