Metadata-Version: 2.4
Name: pyausaxs
Version: 1.0.10
Summary: An efficient small-angle Debye scattering calculator.
Author-email: Kristian Lytje <kristian.lytje@uni-saarland.de>
License-Expression: LGPL-3.0-or-later
Project-URL: Homepage, https://github.com/AUSAXS/pyAUSAXS
Classifier: Programming Language :: Python :: 3
Classifier: Operating System :: OS Independent
Requires-Python: >=3.9
Requires-Dist: py-cpuinfo>=8.0.0
Requires-Dist: numpy>=1.20.0
